{
  "PresetView" : {
    "frame" : {
      "y" : "0",
      "x" : "0",
      "width" : "screen_width",
      "height" : "screen_height",
      "userInteractionEnabled" : "NO"
    },
    "order" : [
      "date",
      "time_",
      "cond",
      "icon",
      "battery",
      "battery_percent"
    ],
    "type" : "UIView",
    "children" : {
      "date" : {
        "borderColor" : "rgba(255,255,255,1)",
        "textStyle" : "none",
        "textAlignment" : "NSTextAlignmentLeft",
        "frame" : {
          "y" : "600",
          "x" : "30",
          "width" : "screen_width",
          "height" : "40"
        },
        "kerning" : "0",
        "backgroundColor" : "rgba(255,255,255,0)",
        "dataAttr" : "none",
        "textColor" : "rgba(255,255,255,1.0)",
        "type" : "UILabel",
        "numberOfLines" : "1",
        "data" : "[day] [month] [date]",
        "borderWidth" : "0",
        "gradientImage" : "none",
        "fontSizeAttr" : "none",
        "fontSize" : "28",
        "fontName" : "Dorsa-Regular.ttf",
        "textShadow" : {
          "y" : "3",
          "color" : "rgba(0,0,0,0)",
          "x" : "0",
          "radius" : "3"
        },
        "fontNameAttr" : "none"
      },
      "time_" : {
        "borderColor" : "rgba(255,255,255,1)",
        "textStyle" : "capitalize",
        "textAlignment" : "NSTextAlignmentLeft",
        "frame" : {
          "y" : "30",
          "x" : "30",
          "width" : "screen_width",
          "height" : "40"
        },
        "kerning" : "0",
        "backgroundColor" : "rgba(255,255,255,0)",
        "dataAttr" : "none",
        "textColor" : "rgba(255, 255, 255, 1.00)",
        "type" : "UILabel",
        "numberOfLines" : "1",
        "data" : "It's [textTime] [devicename]",
        "borderWidth" : "0",
        "gradientImage" : "none",
        "fontSizeAttr" : "none",
        "fontSize" : "28",
        "fontName" : "Dorsa-Regular.ttf",
        "textShadow" : {
          "y" : "3",
          "color" : "rgba(0,0,0,0)",
          "x" : "0",
          "radius" : "3"
        },
        "fontNameAttr" : "none"
      },
      "battery" : {
        "radius" : "2",
        "lowColor" : "rgba(173, 173, 173, 1.00)",
        "backColor" : "rgba(0,0,0,1.0)",
        "frame" : {
          "y" : "FB~25",
          "x" : "center",
          "width" : "math(screen_width-60)",
          "height" : "2"
        },
        "innerColor" : "rgba(255, 255, 255, 1.00)",
        "type" : "BatteryBar",
        "midColor" : "rgba(214, 214, 214, 1.00)",
        "gradientImage" : "none"
      },
      "battery_percent" : {
        "borderColor" : "rgba(255,255,255,1)",
        "textStyle" : "none",
        "textAlignment" : "NSTextAlignmentCenter",
        "frame" : {
          "y" : "FB~35",
          "x" : "center",
          "width" : "150",
          "height" : "40"
        },
        "kerning" : "0",
        "backgroundColor" : "rgba(255,255,255,0)",
        "dataAttr" : "none",
        "textColor" : "rgba(255,255,255,1.0)",
        "type" : "UILabel",
        "numberOfLines" : "1",
        "data" : "[batterypercent]%",
        "borderWidth" : "0",
        "gradientImage" : "none",
        "fontSizeAttr" : "none",
        "fontSize" : "28",
        "fontName" : "Dorsa-Regular.ttf",
        "textShadow" : {
          "y" : "3",
          "radius" : "3",
          "x" : "0",
          "color" : "rgba(0,0,0,0)"
        },
        "fontNameAttr" : "none"
      },
      "cond" : {
        "borderColor" : "rgba(255,255,255,1)",
        "textStyle" : "capitalize",
        "textAlignment" : "NSTextAlignmentLeft",
        "frame" : {
          "y" : "630",
          "x" : "30",
          "width" : "screen_width",
          "height" : "40"
        },
        "kerning" : "0",
        "backgroundColor" : "rgba(255,255,255,0)",
        "dataAttr" : "none",
        "textColor" : "rgba(255,255,255,1.0)",
        "type" : "UILabel",
        "numberOfLines" : "1",
        "data" : "[condition] [temperature][temptype]",
        "borderWidth" : "0",
        "gradientImage" : "none",
        "fontSizeAttr" : "none",
        "fontSize" : "28",
        "fontName" : "Dorsa-Regular.ttf",
        "textShadow" : {
          "y" : "3",
          "color" : "rgba(0,0,0,0)",
          "x" : "0",
          "radius" : "3"
        },
        "fontNameAttr" : "none"
      },
      "icon" : {
        "frame" : {
          "y" : "618",
          "x" : "FR~30",
          "width" : "40",
          "height" : "40"
        },
        "forecast" : "none",
        "type" : "WeatherIcon",
        "iconSet" : "OutlinedW"
      }
    }
  }
}